get_annotations/__init__.py
get_annotations-0.1.1.dist-info/LICENSE
get_annotations-0.1.1.dist-info/WHEEL
get_annotations-0.1.1.dist-info/METADATA
get_annotations-0.1.1.dist-info/RECORD
